grapec/__init__.py
grapec/py.typed
grapec-0.1.0.dist-info/METADATA
grapec-0.1.0.dist-info/WHEEL
grapec-0.1.0.dist-info/RECORD
