Metadata-Version: 2.4
Name: grapec
Version: 0.1.0
Summary: Load protobuf and grpc definition file dynamiclly
Author-email: AN Long <aisk1988@gmail.com>
Requires-Python: >=3.9
Requires-Dist: grpcio-tools>=1.73.0
